kmmate/__init__.py
kmmate/cli.py
kmmate/config.py
kmmate/generate/__init__.py
kmmate/generate/generate.py
kmmate/utils/__init__.py
kmmate/utils/files.py
kmmate/utils/framework.py
kmmate/utils/packages.py
kmmate/utils/sample.py
kmmate-0.1.1.dist-info/WHEEL
kmmate-0.1.1.dist-info/entry_points.txt
kmmate-0.1.1.dist-info/METADATA
kmmate-0.1.1.dist-info/RECORD
