Metadata-Version: 2.1
Name: kmmate
Version: 0.1.1
Summary: The awesome tool for creating KMM projects.
Author: Artem Skopincev
Author-email: sckopincev.artyom@gmail.com
Requires-Python: >=3.11,<4.0
Classifier: Programming Language :: Python :: 3
Classifier: Programming Language :: Python :: 3.11
Requires-Dist: typer[all] (>=0.7.0,<0.8.0)
